vending_machine.v
module vending_machine(
    input clk,
    input reset,
    input coin5,
    input coin10,
    input cancel,

    output reg dispense,
    output reg refund,
    output reg change
);


// State Declaration
parameter S0        = 3'b000;
parameter S5        = 3'b001;
parameter DISPENSE  = 3'b010;
parameter CHANGE    = 3'b011;
parameter REFUND    = 3'b100;

reg [2:0] state, next_state;


// State Register

always @(posedge clk or posedge reset)
begin
    if(reset)
        state <= S0;
    else
        state <= next_state;
end


// Next State Logic

always @(*)
begin

    case(state)

        // Initial State
      
        S0:
        begin
            if(coin10)
                next_state = DISPENSE;

            else if(coin5)
                next_state = S5;

            else
                next_state = S0;
        end

    
        // ₹5 Collected
        
        S5:
        begin
            if(cancel)
                next_state = REFUND;

            else if(coin10)
                next_state = CHANGE;

            else if(coin5)
                next_state = DISPENSE;

            else
                next_state = S5;
        end

        
        // Dispense Product
        
        DISPENSE:
        begin
            next_state = S0;
        end

    
        // Dispense + Change
    
        CHANGE:
        begin
            next_state = S0;
        end

        
        // Refund Money
        
        REFUND:
        begin
            next_state = S0;
        end

        default:
            next_state = S0;

    endcase

end


// Output Logic

always @(*)
begin

    dispense = 0;
    refund   = 0;
    change   = 0;

    case(state)

        DISPENSE:
        begin
            dispense = 1;
        end

        CHANGE:
        begin
            dispense = 1;
            change = 1;
        end

        REFUND:
        begin
            refund = 1;
        end

        default:
        begin
            dispense = 0;
            refund = 0;
            change = 0;
        end

    endcase

end

endmodule

tb_vending_machine.v
`timescale 1ns/1ps

module tb_vending_machine;

reg clk;
reg reset;
reg coin5;
reg coin10;
reg cancel;

wire dispense;
wire refund;
wire change;

// DUT
vending_machine uut(
    .clk(clk),
    .reset(reset),
    .coin5(coin5),
    .coin10(coin10),
    .cancel(cancel),
    .dispense(dispense),
    .refund(refund),
    .change(change)
);

// Clock Generation
always #5 clk = ~clk;

initial
begin

    $dumpfile("vending_machine.vcd");
    $dumpvars(0,tb_vending_machine);

    $display("Time\tReset\t₹5\t₹10\tCancel\tDispense\tRefund\tChange");

    $monitor("%0t\t%b\t%b\t%b\t%b\t%b\t\t%b\t%b",
             $time,reset,coin5,coin10,cancel,
             dispense,refund,change);

    clk=0;
    reset=1;
    coin5=0;
    coin10=0;
    cancel=0;

    // Reset
   
    #10 reset=0;
 
    // Test 1
    // ₹10 Coin
    #10;
    coin10=1;

    #10;
    coin10=0;

    // Test 2
    // ₹5 + ₹5
   
    #20;
    coin5=1;

    #10;
    coin5=0;

    #20;
    coin5=1;

    #10;
    coin5=0;

  
    // Test 3
    // ₹5 + ₹10
    
    #20;
    coin5=1;

    #10;
    coin5=0;

    #20;
    coin10=1;

    #10;
    coin10=0;

   
    // Test 4
    // Cancel Transaction
    
    #20;
    coin5=1;

    #10;
    coin5=0;

    #20;
    cancel=1;

    #10;
    cancel=0;

   
    // Test 5
    // Idle
    
    #40;

    $display("-----------------------------------");
    $display("Simulation Completed Successfully");
    $display("-----------------------------------");

    $finish;

end

endmodule

vending_machine.vcd
$date
	Fri Jun 26 12:46:01 2026
$end
$version
	Icarus Verilog
$end
$timescale
	1ps
$end
$scope module tb_vending_machine $end
$var wire 1 ! refund $end
$var wire 1 " dispense $end
$var wire 1 # change $end
$var reg 1 $ cancel $end
$var reg 1 % clk $end
$var reg 1 & coin10 $end
$var reg 1 ' coin5 $end
$var reg 1 ( reset $end
$scope module uut $end
$var wire 1 $ cancel $end
$var wire 1 % clk $end
$var wire 1 & coin10 $end
$var wire 1 ' coin5 $end
$var wire 1 ( reset $end
$var parameter 3 ) CHANGE $end
$var parameter 3 * DISPENSE $end
$var parameter 3 + REFUND $end
$var parameter 3 , S0 $end
$var parameter 3 - S5 $end
$var reg 1 # change $end
$var reg 1 " dispense $end
$var reg 3 . next_state [2:0] $end
$var reg 1 ! refund $end
$var reg 3 / state [2:0] $end
$upscope $end
$upscope $end
$enddefinitions $end
$comment Show the parameter values. $end
$dumpall
b1 -
b0 ,
b100 +
b10 *
b11 )
$end
#0
$dumpvars
b0 /
b0 .
1(
0'
0&
0%
0$
0#
0"
0!
$end
#5000
1%
#10000
0%
0(
#15000
1%
#20000
b10 .
0%
1&
#25000
1"
b0 .
b10 /
1%
#30000
0%
0&
#35000
0"
b0 /
1%
#40000
0%
#45000
1%
#50000
b1 .
0%
1'
#55000
b10 .
b1 /
1%
#60000
b1 .
0%
0'
#65000
1%
#70000
0%
#75000
1%
#80000
b10 .
0%
1'
#85000
1"
b0 .
b10 /
1%
#90000
0%
0'
#95000
0"
b0 /
1%
#100000
0%
#105000
1%
#110000
b1 .
0%
1'
#115000
b10 .
b1 /
1%
#120000
b1 .
0%
0'
#125000
1%
#130000
0%
#135000
1%
#140000
b11 .
0%
1&
#145000
1#
1"
b0 .
b11 /
1%
#150000
0%
0&
#155000
0#
0"
b0 /
1%
#160000
0%
#165000
1%
#170000
b1 .
0%
1'
#175000
b10 .
b1 /
1%
#180000
b1 .
0%
0'
#185000
1%
#190000
0%
#195000
1%
#200000
b100 .
0%
1$
#205000
1!
b0 .
b100 /
1%
#210000
0%
0$
#215000
0!
b0 /
1%
